mcp_server_trending/__init__.py
mcp_server_trending/config.py
mcp_server_trending/server.py
mcp_server_trending/fetchers/__init__.py
mcp_server_trending/fetchers/base.py
mcp_server_trending/fetchers/aggregation/__init__.py
mcp_server_trending/fetchers/aggregation/fetcher.py
mcp_server_trending/fetchers/aitools/__init__.py
mcp_server_trending/fetchers/aitools/fetcher.py
mcp_server_trending/fetchers/alternativeto/__init__.py
mcp_server_trending/fetchers/alternativeto/fetcher.py
mcp_server_trending/fetchers/arxiv/__init__.py
mcp_server_trending/fetchers/arxiv/fetcher.py
mcp_server_trending/fetchers/awesome/__init__.py
mcp_server_trending/fetchers/awesome/fetcher.py
mcp_server_trending/fetchers/betalist/__init__.py
mcp_server_trending/fetchers/betalist/fetcher.py
mcp_server_trending/fetchers/chrome/__init__.py
mcp_server_trending/fetchers/chrome/fetcher.py
mcp_server_trending/fetchers/codepen/__init__.py
mcp_server_trending/fetchers/codepen/fetcher.py
mcp_server_trending/fetchers/cross_platform/__init__.py
mcp_server_trending/fetchers/cross_platform/fetcher.py
mcp_server_trending/fetchers/devto/__init__.py
mcp_server_trending/fetchers/devto/fetcher.py
mcp_server_trending/fetchers/echojs/__init__.py
mcp_server_trending/fetchers/echojs/fetcher.py
mcp_server_trending/fetchers/github/__init__.py
mcp_server_trending/fetchers/github/fetcher.py
mcp_server_trending/fetchers/gumroad/__init__.py
mcp_server_trending/fetchers/gumroad/fetcher.py
mcp_server_trending/fetchers/hackernews/__init__.py
mcp_server_trending/fetchers/hackernews/fetcher.py
mcp_server_trending/fetchers/hashnode/__init__.py
mcp_server_trending/fetchers/hashnode/fetcher.py
mcp_server_trending/fetchers/huggingface/__init__.py
mcp_server_trending/fetchers/huggingface/fetcher.py
mcp_server_trending/fetchers/indiehackers/__init__.py
mcp_server_trending/fetchers/indiehackers/fetcher.py
mcp_server_trending/fetchers/juejin/__init__.py
mcp_server_trending/fetchers/juejin/fetcher.py
mcp_server_trending-0.1.5.dist-info/licenses/LICENSE
mcp_server_trending-0.1.5.dist-info/METADATA
mcp_server_trending-0.1.5.dist-info/WHEEL
mcp_server_trending-0.1.5.dist-info/entry_points.txt
mcp_server_trending-0.1.5.dist-info/top_level.txt
mcp_server_trending-0.1.5.dist-info/RECORD
