Metadata-Version: 2.4
Name: mcp-server-trending
Version: 0.1.5
Summary: MCP Server for trending data from multiple platforms for indie developers
Author: MCP Server Trending Team
License-Expression: MIT
Project-URL: Homepage, https://github.com/Talljack/mcp_server_trending
Project-URL: Documentation, https://github.com/Talljack/mcp_server_trending#readme
Project-URL: Repository, https://github.com/Talljack/mcp_server_trending
Project-URL: Issues, https://github.com/Talljack/mcp_server_trending/issues
Keywords: mcp,trending,github,hackernews,producthunt,indie-hackers
Classifier: Development Status :: 3 - Alpha
Classifier: Intended Audience :: Developers
Classifier: Programming Language :: Python :: 3
Classifier: Programming Language :: Python :: 3.10
Classifier: Programming Language :: Python :: 3.11
Classifier: Programming Language :: Python :: 3.12
Requires-Python: >=3.10
License-File: LICENSE
Requires-Dist: mcp>=1.0.0
Requires-Dist: smithery>=0.3.1
Requires-Dist: httpx>=0.27.0
Requires-Dist: beautifulsoup4>=4.12.0
Requires-Dist: ruff>=0.14.5
Requires-Dist: praw>=7.7.0
Requires-Dist: playwright>=1.40.0
Provides-Extra: dev
Requires-Dist: pytest>=7.0.0; extra == "dev"
Requires-Dist: pytest-asyncio>=0.21.0; extra == "dev"
Requires-Dist: black>=23.0.0; extra == "dev"
Requires-Dist: ruff>=0.1.0; extra == "dev"
Requires-Dist: mypy>=1.0.0; extra == "dev"
Dynamic: license-file
